docx2json/__init__.py
docx2json-0.0.10.dist-info/LICENSE
docx2json-0.0.10.dist-info/METADATA
docx2json-0.0.10.dist-info/WHEEL
docx2json-0.0.10.dist-info/top_level.txt
docx2json-0.0.10.dist-info/RECORD
