Metadata-Version: 2.1
Name: docx2json
Version: 0.0.10
Summary: Python script that converts text from a .docx file to .json.
Home-page: https://github.com/andremsouza/docx2json
Author: andremsouza
Author-email: msouza.andre@hotmail.com
License: UNKNOWN
Platform: UNKNOWN
Classifier: Programming Language :: Python :: 3
Classifier: License :: OSI Approved :: MIT License
Classifier: Operating System :: OS Independent
Requires-Dist: python-docx
